README.md
setup.py
fracture/__init__.py
fracture/_access.py
fracture/_element.py
fracture/_project.py
fracture/_scan.py
fracture/_utils.py
fracture/constants.py
fracture.egg-info/PKG-INFO
fracture.egg-info/SOURCES.txt
fracture.egg-info/dependency_links.txt
fracture.egg-info/requires.txt
fracture.egg-info/top_level.txt
fracture/_res/fracture.png
fracture/_res/fracture_65.png
fracture/_res/fracture_65_black.png
fracture/built-in/filescanner.py
fracture/sql/add.sql
fracture/sql/create.sql
fracture/sql/find.sql
fracture/sql/find_all.sql
fracture/sql/remove.sql
fracture/sql/settings_get.sql
fracture/sql/settings_set.sql
fracture/sql/tag_connect.sql
fracture/sql/tag_insert.sql
fracture/sql/tags_add.sql
fracture/sql/tags_get.sql
fracture/sql/tags_rem.sql