Metadata-Version: 2.1
Name: fracture
Version: 0.9.2
Summary: Fracture is a lightweight and flexible data management system
Home-page: https://github.com/mikemalinowski/fracture
Author: Mike Malinowski
Author-email: mike@twisted.space
License: UNKNOWN
Keywords: fracture data composite
Platform: UNKNOWN
Classifier: Programming Language :: Python
Classifier: License :: OSI Approved :: MIT License
Classifier: Operating System :: OS Independent
